graphql_api/__init__.py
graphql_api/api.py
graphql_api/context.py
graphql_api/dataclass_mapping.py
graphql_api/decorators.py
graphql_api/directives.py
graphql_api/error.py
graphql_api/exception.py
graphql_api/executor.py
graphql_api/mapper.py
graphql_api/middleware.py
graphql_api/mutation_schema.py
graphql_api/pydantic.py
graphql_api/pydantic_utils.py
graphql_api/reduce.py
graphql_api/relay.py
graphql_api/remote.py
graphql_api/schema.py
graphql_api/schema_filter.py
graphql_api/type_utils.py
graphql_api/types.py
graphql_api/utils.py
graphql_api/federation/__init__.py
graphql_api/federation/directives.py
graphql_api/federation/federation.py
graphql_api/federation/types.py
graphql_api-1.6.1.dist-info/licenses/LICENSE
graphql_api-1.6.1.dist-info/METADATA
graphql_api-1.6.1.dist-info/WHEEL
graphql_api-1.6.1.dist-info/top_level.txt
graphql_api-1.6.1.dist-info/RECORD
