Metadata-Version: 2.4
Name: graphql-api
Version: 1.6.1
Summary: A framework for building Python GraphQL APIs.
Author-email: Robert Parker <rob@parob.com>
License: MIT
Project-URL: Homepage, https://gitlab.com/parob/graphql-api
Project-URL: Repository, https://gitlab.com/parob/graphql-api
Keywords: GraphQL,GraphQL-API,GraphQLAPI,Server
Classifier: Development Status :: 3 - Alpha
Classifier: Intended Audience :: Developers
Classifier: Programming Language :: Python :: 3
Classifier: License :: OSI Approved :: MIT License
Classifier: Operating System :: OS Independent
Requires-Python: <3.13,>=3.11
License-File: LICENSE
Requires-Dist: graphql-core
Requires-Dist: requests
Requires-Dist: typing-inspect
Requires-Dist: aiohttp
Requires-Dist: docstring-parser
Requires-Dist: pydantic
Dynamic: license-file
